CHANGELOG.txt
LICENCE.txt
MANIFEST.in
README.txt
setup.py
secure_password/__init__.py
secure_password_py.egg-info/PKG-INFO
secure_password_py.egg-info/SOURCES.txt
secure_password_py.egg-info/dependency_links.txt
secure_password_py.egg-info/top_level.txt