Metadata-Version: 1.1
Name: secure-password-py
Version: 0.0.0
Summary: A very easy password generator
Home-page: UNKNOWN
Author: Invisible Medusa
Author-email: invisiblemedusa10@gmail.com
License: MIT
Keywords: password generator
Platform: UNKNOWN
Classifier: Development Status :: 5 - Production/Stable
Classifier: Intended Audience :: Education
Classifier: Operating System :: Microsoft :: Windows :: Windows 10
Classifier: License :: OSI Approved :: MIT License
Classifier: Programming Language :: Python :: 3
